RotationDetector/Config.py
RotationDetector/__init__.py
RotationDetector/detect.py
RotationDetector/detect_onnx.py
RotationDetector/test.py
RotationDetector/torch2onnx.py
RotationDetector/train.py
RotationDetector/RotationModelTools/__init__.py
RotationDetector/RotationModelTools/augments.py
RotationDetector/RotationModelTools/load.py
RotationDetector/RotationModelTools/plot.py
RotationDetector/RotationModelTools/post_process.py
RotationDetector/RotationModelTools/scheduler.py
RotationDetector/RotationModelTools/utils.py
RotationDetector/RotationModelYolov4/__init__.py
RotationDetector/RotationModelYolov4/backbone.py
RotationDetector/RotationModelYolov4/head.py
RotationDetector/RotationModelYolov4/model.py
RotationDetector/RotationModelYolov4/neck.py
RotationDetector/RotationModelYolov4/utils.py
RotationDetector/RotationModelYolov4/yololayer.py
RotationDetector/checkDataFormat/__init__.py
RotationDetector/checkDataFormat/checkDir.py
RotationDetector-1.0.0.dist-info/METADATA
RotationDetector-1.0.0.dist-info/WHEEL
RotationDetector-1.0.0.dist-info/top_level.txt
RotationDetector-1.0.0.dist-info/RECORD
