Metadata-Version: 2.1
Name: RotationDetector
Version: 1.0.0
Summary: Simple and general rotation detection framework 
Home-page: https://dev.skyvm.com/wkx12138/
Author: xidian wkx
Author-email: 1594609920@qq.com
License: UNKNOWN
Platform: UNKNOWN
Requires-Dist: matplotlib (>=3.4.2)
Requires-Dist: numpy (>=1.20.3)
Requires-Dist: onnxruntime (>=1.8.1)
Requires-Dist: opencv-python (>=4.5.1.48)
Requires-Dist: Pillow (>=9.0.1)
Requires-Dist: Shapely (>=1.7.1)
Requires-Dist: tqdm (>=4.61.0)
